zproc/__init__.py
zproc/__version__.py
zproc/child.py
zproc/consts.py
zproc/context.py
zproc/exceptions.py
zproc/process.py
zproc/serializer.py
zproc/util.py
zproc/server/__init__.py
zproc/server/main.py
zproc/server/tools.py
zproc/state/__init__.py
zproc/state/_type.py
zproc/state/server.py
zproc/state/state.py
zproc/task/__init__.py
zproc/task/map_plus.py
zproc/task/result.py
zproc/task/server.py
zproc/task/swarm.py
zproc/task/worker.py
zproc-0.9.5.dist-info/LICENSE
zproc-0.9.5.dist-info/METADATA
zproc-0.9.5.dist-info/WHEEL
zproc-0.9.5.dist-info/top_level.txt
zproc-0.9.5.dist-info/RECORD
