Metadata-Version: 2.1
Name: zproc
Version: 0.9.5
Summary: ZProc - Multi Processing on steroids
Home-page: https://github.com/devxpy/zproc
Author: Dev Aggarwal
Author-email: devxpy@gmail.com
License: MIT
Platform: UNKNOWN
Classifier: License :: OSI Approved :: MIT License
Classifier: Programming Language :: Python
Classifier: Programming Language :: Python :: 3
Classifier: Programming Language :: Python :: 3.6
Classifier: Programming Language :: Python :: 3.7
Classifier: Programming Language :: Python :: Implementation :: CPython
Requires-Python: >=3.6
Requires-Dist: pyzmq
Requires-Dist: tblib
Requires-Dist: psutil
Requires-Dist: cloudpickle
